LICENSE
README.md
setup.py
ptbmod/__init__.py
ptbmod/__version__.py
ptbmod/config.py
ptbmod.egg-info/PKG-INFO
ptbmod.egg-info/SOURCES.txt
ptbmod.egg-info/dependency_links.txt
ptbmod.egg-info/requires.txt
ptbmod.egg-info/top_level.txt
ptbmod/decorator/__init__.py
ptbmod/decorator/admins.py
ptbmod/decorator/cache.py
ptbmod/decorator/command.py
ptbmod/decorator/handlers.py