Metadata-Version: 2.4
Name: ptbmod
Version: 0.5
Summary: Patch for python-telegram-bot providing decorator support for easy command handling and admin verification.
Home-page: https://github.com/AshokShau/ptbmod
Download-URL: https://github.com/AshokShau/ptbmod/releases/latest
Author: AshokShau (Ashok)
Author-email: <abishnoi69@outlook.com>
License: MIT
Project-URL: Tracker, https://github.com/AshokShau/ptbmod/issues
Project-URL: Community, https://t.me/GuardxSupport
Project-URL: Source, https://github.com/AshokShau/ptbmod
Project-URL: Documentation, https://t.me/GuardxSupport
Keywords: telegram telegram-bot bot python-telegram-bot decorators command handling admin verification
Classifier: Development Status :: 5 - Production/Stable
Classifier: Intended Audience :: Developers
Classifier: Natural Language :: English
Classifier: Operating System :: OS Independent
Classifier: Programming Language :: Python
Classifier: Programming Language :: Python :: 3
Classifier: Programming Language :: Python :: 3.8
Classifier: Programming Language :: Python :: 3.9
Classifier: Programming Language :: Python :: 3.10
Classifier: Programming Language :: Python :: 3.11
Classifier: Programming Language :: Python :: 3.12
Classifier: Programming Language :: Python :: 3.13
Classifier: Programming Language :: Python :: Implementation
Classifier: Programming Language :: Python :: Implementation :: CPython
Classifier: Programming Language :: Python :: Implementation :: PyPy
Classifier: Topic :: Internet
Classifier: Topic :: Communications
Classifier: Topic :: Communications :: Chat
Classifier: Topic :: Software Development :: Libraries
Classifier: Topic :: Software Development :: Libraries :: Python Modules
Classifier: Topic :: Software Development :: Libraries :: Application Frameworks
Requires-Python: >=3.8
License-File: LICENSE
Requires-Dist: python-dotenv
Provides-Extra: all
Requires-Dist: python-telegram-bot[callback-data]; extra == "all"
Dynamic: author
Dynamic: author-email
Dynamic: classifier
Dynamic: description
Dynamic: description-content-type
Dynamic: download-url
Dynamic: home-page
Dynamic: keywords
Dynamic: license
Dynamic: license-file
Dynamic: project-url
Dynamic: provides-extra
Dynamic: requires-dist
Dynamic: requires-python
Dynamic: summary
